reachy_mini_motor_controller-1.5.3.dist-info/METADATA
reachy_mini_motor_controller-1.5.3.dist-info/WHEEL
reachy_mini_motor_controller.libs/libgcc_s-6d2d9dc8.so.1
reachy_mini_motor_controller/__init__.py
reachy_mini_motor_controller/__init__.pyi
reachy_mini_motor_controller/py.typed
reachy_mini_motor_controller/reachy_mini_motor_controller.cpython-312-x86_64-linux-musl.so
reachy_mini_motor_controller-1.5.3.dist-info/RECORD
